{
    "title": "affa",
    "text": "afa",
    "hashtags": "af",
    "media_type": "None",
    "media_paths": [],
    "platforms": {
        "Facebook": true,
        "Instagram": false,
        "Twitter": false,
        "LinkedIn": false
    },
    "facebook_options": {
        "story_selected": false,
        "post_selected": true,
        "story_options": "",
        "post_options": {
            "Only Text": true,
            "Only Image": false,
            "Only Video": false,
            "All": false
        }
    },
    "linkedin_option": "None",
    "instagram_options": {
        "Post": false,
        "Reel": false,
        "Story": false
    },
    "instagram_post_orientation": "",
    "instagram_reel_orientation": "",
    "twitter_options": {
        "Only Text": false,
        "Only Videos": false,
        "Only Images": false,
        "All": false
    },
    "schedule_post": false,
    "schedule_time": "",
    "repeat_frequency": "None"
}